{"card_name": "Paradox of Might", "color": "BG", "rarity": "common", "type": "Creature \u2013 Weird", "number": 204, "color_identity": "BG", "cost": "{2}{BG}", "rules_text": "Paradox of Might enters the battlefield with two +1/+1 counters on it.\nWhen Paradox of Might dies, put its counters on up to one target creature.", "flavor_text": "[i]It watches the hunt carefully, waiting for the day it can show its predators true strength.[/i]", "pt": "0/0", "special_text": "", "shape": "normal", "set": "TZR", "loyalty": "", "artist": "Peter Mohrbacher", "notes": "", "image_type": "png"}