{"card_name": "Sorrowful Maiden", "color": "W", "rarity": "uncommon", "type": "Creature \u2013 Human Noble", "number": 24, "color_identity": "W", "cost": "{W}", "rules_text": "Sacrifice Sorrowful Maiden: Put a +1/+1 counter on each creature that entered the battlefield under your control this turn.", "flavor_text": "[i]Many suitors came along, but she keeps on waiting for her love to return.[/i]", "pt": "1/1", "special_text": "", "shape": "normal", "set": "TZR", "loyalty": "", "artist": "WLOP", "notes": "", "image_type": "png"}