{"card_name": "Friendly Skywatcher", "color": "W", "rarity": "common", "type": "Creature \u2013 Dragon", "number": 8, "color_identity": "W", "cost": "{3}{W}", "rules_text": "Flying\nWhenever Friendly Skywatcher attacks, you may pay {1}{W}. If you do, target attacking creature gains flying until end of turn.", "flavor_text": "[i]\u201cTo ride a dragon's back\u201d\n\u2014Zhi-Qiang saying meaning \u201cTake a risk\u201d[/i]", "pt": "3/2", "special_text": "", "shape": "normal", "set": "TZR", "loyalty": "", "artist": "Dogan Oztel", "notes": "", "image_type": "png"}